askbot/__init__.py
askbot/admin.py
askbot/api.py
askbot/apps.py
askbot/auth.py
askbot/context.py
askbot/exceptions.py
askbot/feed.py
askbot/forms.py
askbot/search_indexes.py
askbot/signals.py
askbot/sitemap.py
askbot/startup_procedures.py
askbot/tasks.py
askbot/urls.py
askbot/bin/__init__.py
askbot/bin/checklocales.py
askbot/bin/dos2unix.sh
askbot/bin/generate_modules.py
askbot/bin/mergelocales.py
askbot/bin/rebuildlocales.py
askbot/bin/test_permission_assertions
askbot/conf/README
askbot/conf/__init__.py
askbot/conf/access_control.py
askbot/conf/badges.py
askbot/conf/email.py
askbot/conf/email_text.py
askbot/conf/external_keys.py
askbot/conf/feedback.py
askbot/conf/flatpages.py
askbot/conf/forum_data_rules.py
askbot/conf/group_settings.py
askbot/conf/karma_and_badges_visibility.py
askbot/conf/ldap.py
askbot/conf/leading_sidebar.py
askbot/conf/license.py
askbot/conf/login_providers.py
askbot/conf/markup.py
askbot/conf/minimum_reputation.py
askbot/conf/moderation.py
askbot/conf/question_lists.py
askbot/conf/reputation_changes.py
askbot/conf/settings_wrapper.py
askbot/conf/sidebar_main.py
askbot/conf/sidebar_profile.py
askbot/conf/sidebar_question.py
askbot/conf/site_modes.py
askbot/conf/site_settings.py
askbot/conf/skin_general_settings.py
askbot/conf/social_sharing.py
askbot/conf/spam_and_moderation.py
askbot/conf/static_settings.py
askbot/conf/super_groups.py
askbot/conf/user_settings.py
askbot/conf/vote_rules.py
askbot/conf/words.py
askbot/const/__init__.py
askbot/const/message_keys.py
askbot/container/Dockerfile.redis
askbot/container/cron-askbot.sh
askbot/container/crontab
askbot/container/docker-compose.yml
askbot/container/postgres_init.sql
askbot/container/prestart.py
askbot/container/prestart.sh
askbot/container/uwsgi.ini
askbot/cron/README
askbot/cron/askbot_cron_job
askbot/deployment/__init__.py
askbot/deployment/console.py
askbot/deployment/const.py
askbot/deployment/deployments.md
askbot/deployment/exceptions.py
askbot/deployment/messages.del.py
askbot_selimgul-0.11.0.dist-info/AUTHORS
askbot_selimgul-0.11.0.dist-info/COPYING
askbot_selimgul-0.11.0.dist-info/LICENSE
askbot_selimgul-0.11.0.dist-info/METADATA
askbot_selimgul-0.11.0.dist-info/WHEEL
askbot_selimgul-0.11.0.dist-info/entry_points.txt
askbot_selimgul-0.11.0.dist-info/top_level.txt
askbot_selimgul-0.11.0.dist-info/RECORD
