Metadata-Version: 2.1
Name: askbot-selimgul
Version: 0.11.0
Summary: Question and Answer forum, like StackOverflow, written in python and Django
Home-page: http://askbot.org
Author: Selim.Gul
Author-email: selimgul@gmail.com
License: GPLv3
Keywords: forum,community,wiki,Q&A
Platform: UNKNOWN
Classifier: Development Status :: 4 - Beta
Classifier: Environment :: Web Environment
Classifier: Framework :: Django
Classifier: Intended Audience :: Developers
Classifier: License :: OSI Approved :: GNU General Public License (GPL)
Classifier: Natural Language :: English
Classifier: Natural Language :: Finnish
Classifier: Natural Language :: German
Classifier: Natural Language :: Russian
Classifier: Natural Language :: Serbian
Classifier: Natural Language :: Turkish
Classifier: Operating System :: OS Independent
Classifier: Programming Language :: Python :: 3
Classifier: Programming Language :: JavaScript
Classifier: Topic :: Communications :: Usenet News
Classifier: Topic :: Communications :: Email :: Mailing List Servers
Classifier: Topic :: Communications
Classifier: Topic :: Internet :: WWW/HTTP :: WSGI :: Application
Requires-Dist: django-appconf (==1.0.3)
Requires-Dist: akismet (==1.0.1)
Requires-Dist: django-avatar (>=4.0)
Requires-Dist: beautifulsoup4 (<=4.7.1)
Requires-Dist: django-compressor (<=2.4,>=2.0)
Requires-Dist: django (<3.0,>=1.11)
Requires-Dist: django-countries (>=3.3)
Requires-Dist: django-jinja (>=2.0)
Requires-Dist: celery (<5.0,>=4.0)
Requires-Dist: django-followit (==0.4.1)
Requires-Dist: html5lib (==0.9999999)
Requires-Dist: Jinja2 (>=2.10)
Requires-Dist: jsonfield (>=2.0.0)
Requires-Dist: pyjwt (<=1.7.1)
Requires-Dist: django-keyedcache3 (>=1.5.1)
Requires-Dist: django-livesettings3 (==1.4.20)
Requires-Dist: markdown2 (<=2.3.9)
Requires-Dist: mock (==3.0.5)
Requires-Dist: oauth2 (<=1.9.0.post1)
Requires-Dist: python-openid2 (>=3.0)
Requires-Dist: django-picklefield (>=1.0.0)
Requires-Dist: pytz
Requires-Dist: django-recaptcha (<=1.3.0,>=1.0.3)
Requires-Dist: python-cas (<1.6,>=1.4.0)
Requires-Dist: responses (>=0.9.0)
Requires-Dist: requests-oauthlib (>=1.2.0)
Requires-Dist: requirements-parser (>=0.2.0)
Requires-Dist: django-robots (>=3.1)
Requires-Dist: regex
Requires-Dist: django-tinymce (>=2.8.0)
Requires-Dist: unidecode
